einstein_models/__init__.py
einstein_models/einstein_models.py
einstein_models/constant/__init__.py
einstein_models/constant/constants.py
einstein_models/data/__init__.py
einstein_models/data/chat_messages.py
einstein_models/data/chat_response.py
einstein_models/data/definitions.py
einstein_models/data/embedding_objects.py
einstein_models/models/__init__.py
einstein_models/models/embedding_models.py
einstein_models/models/models.py
einstein_models/rest/authenticate.py
einstein_models/rest/chat_generation.py
einstein_models/rest/generate.py
einstein_models/rest/generate_embedding.py
einstein_models-0.2.5.dist-info/LICENSE
einstein_models-0.2.5.dist-info/METADATA
einstein_models-0.2.5.dist-info/WHEEL
einstein_models-0.2.5.dist-info/top_level.txt
einstein_models-0.2.5.dist-info/RECORD
