Metadata-Version: 2.1
Name: einstein-models
Version: 0.2.5
Summary: Python SDK for Salesforce Einstein Models API
Home-page: https://github.com/amirkhan-ak-sf/einstein-models
Author: Amir Khan
Author-email: amir.khan@salesforce.com
License: UNKNOWN
Platform: UNKNOWN
Classifier: Programming Language :: Python :: 3
Classifier: License :: OSI Approved :: MIT License
Classifier: Operating System :: OS Independent
Requires-Python: >=3.6
Requires-Dist: requests
Requires-Dist: python-dotenv
